<contentList>
	<content contentuid="h2046e8b0g91dfg40f1g8603gfa569de1c0fd">Forgetinator - Safety ON</content>
	<content contentuid="h2a9a7ca6g2603g4213g8624g4fe65ea06b4f">This wooden stick produces an intense flash of light that can reorganize neural synapses in the host&apos;s brain. Can be used to selectively purge memories or for a total memory wipe. Warning: Effects of long term exposure are unknown.</content>
	<content contentuid="h5d9d0b2cg8826g48ffg81fdg571f2474dd37">Forgetinator</content>
	<content contentuid="h680843e8g707eg4022g9465gb38a3912e75c">This wooden stick produces an intense flash of light that can reorganize neural synapses in the host&apos;s brain. Can be used to selectively purge memories or for a total memory wipe. The safety cap has been pryed off. &lt;font color=#FF0000&gt;Warning: The Safety features have been turned off and the device is running at max capacity. CAUTION ADVISED. Any skills (innate, item-granted, status-granted etc.) not on the skillbar/hotbar will be removed.&lt;/font&gt;</content>
	<content contentuid="h8311eb63g89cfg41c1g961cgde31f8d79927"></content>
	<content contentuid="hc6972a92g0b81g4bd4g9445g9fdbf6bb44c2">Forgetinator - Safety OFF</content>
	<content contentuid="hd3c8a3ceg6c8eg44b1g8f38g427a068869d6">Forgetinator - Safety OFF</content>
	<content contentuid="hf35f9c26gc943g410bg924cge7fa2bc5089c">Forgetinator</content>
	<content contentuid="hf60e9317g553fg4e48ga3c2gc01b3d4e1f79">Forgetinator - Safety OFF</content>
</contentList>
